actions/__init__.py
actions/api_main.py
actions/convert.py
actions/handler.py
actions/handler_texts.yaml
actions/manage.py
actions/measure.py
actions/verify.py
convertors/__init__.py
convertors/convertors_config.py
convertors/convertors_config.yaml
convertors/convertors_texts.yaml
convertors/confluence_convertor/__init__.py
convertors/confluence_convertor/convertor.py
convertors/confluence_convertor/reader.py
convertors/gdoc_convertor/__init__.py
convertors/gdoc_convertor/convertor.py
convertors/gdoc_convertor/reader.py
convertors/html_convertor/__init__.py
convertors/html_convertor/convertor.py
convertors/html_convertor/query.py
data/__init__.py
data/data_config.py
data/find.py
data/get.py
data/key.py
data/map.py
data/output.py
data/value.py
language/__init__.py
language/translate.py
language/translate.yaml
manage/__init__.py
manage/manage_config.py
manage/manage_config.yaml
manage/manage_output.py
manage/manage_storage.py
manage/manage_texts.yaml
manage/metadata.py
measure/__init__.py
measure/measure_config.py
measure/measure_config.yaml
measure/measure_distance.py
measure/measure_output.py
measure/measure_texts.yaml
providers/__init__.py
providers/api.py
providers/aws_lambda.py
providers/cli.py
providers/provider.py
providers/providers_config.yaml
providers/providers_dispatch.yaml
response/__init__.py
response/html_response.py
response/response.py
response/response_config.py
response/response_config.yaml
response/response_texts.yaml
schemes/__init__.py
schemes/confluence-scheme-1.0.yaml
schemes/googledoc-scheme-1.0.yaml
schemes/schemes.py
schemes/schemes.yaml
storage/__init__.py
storage/git_permanent_repo.py
storage/gitrepo.py
utils/__init__.py
utils/config.py
utils/error.py
utils/keymaster.py
utils/load_modules.py
utils/load_yaml.py
utils/logging.py
utils/match.py
utils/model.py
utils/output.py
utils/output_texts.yaml
utils/property_str.py
utils/request.py
utils/shell.py
utils/tags.py
utils/text_query.py
utils/transform.py
utils/value_query.py
threatware-0.9.5.1.dist-info/LICENSE
threatware-0.9.5.1.dist-info/METADATA
threatware-0.9.5.1.dist-info/WHEEL
threatware-0.9.5.1.dist-info/entry_points.txt
threatware-0.9.5.1.dist-info/top_level.txt
threatware-0.9.5.1.dist-info/RECORD
