Metadata-Version: 2.1
Name: threatware
Version: 0.9.5.1
Summary: Simplifies the review and management of threat models in documents
Home-page: https://github.com/samadhicsec/threatware
Author: samadhicsecurity
Author-email: dave@samadhicsecurity.com
Project-URL: Documentation, https://threatware.readthedocs.io/en/main/
Project-URL: Tracker, https://github.com/samadhicsec/threatware/issues
Classifier: Programming Language :: Python :: 3.9
Classifier: Development Status :: 4 - Beta
Classifier: License :: OSI Approved :: Apache Software License
Classifier: Operating System :: POSIX :: Linux
Classifier: Topic :: Security
Requires-Python: >=3.9
License-File: LICENSE
Requires-Dist: atlassian-python-api >=3.41.16
Requires-Dist: boto3 >=1.35.32
Requires-Dist: google-api-python-client >=2.147.0
Requires-Dist: google-auth-oauthlib >=1.2.1
Requires-Dist: html2text >=2024.2.26
Requires-Dist: html-table-parser-python3 >=0.3.1
Requires-Dist: Jinja2 >=3.1.3
Requires-Dist: jsonpickle >=3.3.0
Requires-Dist: lxml >=5.3.0
Requires-Dist: python-dateutil >=2.8.2
Requires-Dist: ruamel.yaml >=0.18.6
Requires-Dist: sh >=2.0.7
